Metadata-Version: 2.1
Name: anti-war-handbook-package
Version: 0.0.1
Summary: anti war handbook
Home-page: https://github.com/lushios/anti-war-handbook
Author: Lushios
Author-email: author@example.com
License: UNKNOWN
Project-URL: Bug Tracker, https://github.com/lushios/anti-war-handbook/issues
Platform: UNKNOWN
Classifier: Programming Language :: Python :: 3
Classifier: License :: OSI Approved :: MIT License
Classifier: Operating System :: OS Independent
Requires-Python: >=3.6
License-File: LICENSE
